Metadata-Version: 1.1
Name: cinema
Version: 0.0.8
Summary: Everything about Cinema!
Home-page: https://github.com/meysammahfouzi/cinema
Author: Meysam Mahfouzi, Majid Hajiloo
Author-email: maysam.mahfouzi@gmail.com, majid.hajiloo@gmail.com
License: MIT
Download-URL: https://github.com/meysammahfouzi/cinema/tarball/0.0.8
Keywords: movie,rating,imdb,film,cinema,actor,metascore,tomatometer
Platform: UNKNOWN
Classifier: Intended Audience :: Developers
Classifier: License :: OSI Approved :: MIT License
Classifier: Natural Language :: English
Classifier: Programming Language :: Python
Classifier: Programming Language :: Python :: 2
Classifier: Programming Language :: Python :: 2.7
Classifier: Programming Language :: Python :: 3
Classifier: Programming Language :: Python :: 3.3
Classifier: Programming Language :: Python :: 3.4
Classifier: Programming Language :: Python :: 3.5
Classifier: Programming Language :: Python :: 3.6
Classifier: Programming Language :: Python :: Implementation :: CPython
Classifier: Programming Language :: Python :: Implementation :: PyPy
Classifier: Topic :: Software Development :: Libraries :: Python Modules
